{
  "baseline": {
    "metrics": {
      "mode": "baseline",
      "alpha": 0.0,
      "alpha_mode": "fixed",
      "capacity": 11,
      "headroom": 0.8,
      "ilp_score": 0.0,
      "total_carbon_kg": 560.44,
      "avg_latency_ms": 0.0,
      "p95_latency_ms": 0.0,
      "home_ratio": 1.0,
      "dropped": 0,
      "n_jobs": 2800,
      "energy_kwh": 1939.5,
      "region_load": {
        "US_West": 350,
        "US_Central": 350,
        "US_East": 350,
        "France": 350,
        "Germany": 350,
        "Korea": 350,
        "India": 350,
        "Japan": 350
      }
    },
    "routing_matrix": [
      [
        350,
        0,
        0,
        0,
        0,
        0,
        0,
        0
      ],
      [
        0,
        350,
        0,
        0,
        0,
        0,
        0,
        0
      ],
      [
        0,
        0,
        350,
        0,
        0,
        0,
        0,
        0
      ],
      [
        0,
        0,
        0,
        350,
        0,
        0,
        0,
        0
      ],
      [
        0,
        0,
        0,
        0,
        350,
        0,
        0,
        0
      ],
      [
        0,
        0,
        0,
        0,
        0,
        350,
        0,
        0
      ],
      [
        0,
        0,
        0,
        0,
        0,
        0,
        350,
        0
      ],
      [
        0,
        0,
        0,
        0,
        0,
        0,
        0,
        350
      ]
    ]
  },
  "alpha_0": {
    "metrics": {
      "mode": "ilp",
      "alpha": 0.0,
      "alpha_mode": "fixed",
      "capacity": 11,
      "headroom": 0.8,
      "ilp_score": 7.9,
      "total_carbon_kg": 561.28,
      "avg_latency_ms": 0.69,
      "p95_latency_ms": 0.0,
      "home_ratio": 0.9889,
      "dropped": 0,
      "n_jobs": 2800,
      "energy_kwh": 1939.5,
      "region_load": {
        "US_West": 350,
        "US_Central": 350,
        "US_East": 354,
        "France": 349,
        "Germany": 349,
        "Korea": 350,
        "India": 351,
        "Japan": 347
      }
    },
    "routing_matrix": [
      [
        347,
        3,
        0,
        0,
        0,
        0,
        0,
        0
      ],
      [
        1,
        344,
        2,
        3,
        0,
        0,
        0,
        0
      ],
      [
        0,
        2,
        347,
        1,
        0,
        0,
        0,
        0
      ],
      [
        0,
        1,
        2,
        345,
        2,
        0,
        0,
        0
      ],
      [
        0,
        0,
        3,
        0,
        347,
        0,
        0,
        0
      ],
      [
        0,
        0,
        0,
        0,
        0,
        346,
        0,
        4
      ],
      [
        0,
        0,
        0,
        0,
        0,
        0,
        350,
        0
      ],
      [
        2,
        0,
        0,
        0,
        0,
        4,
        1,
        343
      ]
    ]
  },
  "alpha_0.1": {
    "metrics": {
      "mode": "ilp",
      "alpha": 0.1,
      "alpha_mode": "fixed",
      "capacity": 11,
      "headroom": 0.8,
      "ilp_score": 145.3,
      "total_carbon_kg": 528.21,
      "avg_latency_ms": 1.22,
      "p95_latency_ms": 12.0,
      "home_ratio": 0.9439,
      "dropped": 0,
      "n_jobs": 2800,
      "energy_kwh": 1939.5,
      "region_load": {
        "US_West": 350,
        "US_Central": 351,
        "US_East": 354,
        "France": 456,
        "Germany": 242,
        "Korea": 351,
        "India": 350,
        "Japan": 346
      }
    },
    "routing_matrix": [
      [
        347,
        3,
        0,
        0,
        0,
        0,
        0,
        0
      ],
      [
        1,
        344,
        1,
        4,
        0,
        0,
        0,
        0
      ],
      [
        0,
        2,
        348,
        0,
        0,
        0,
        0,
        0
      ],
      [
        0,
        1,
        3,
        334,
        12,
        0,
        0,
        0
      ],
      [
        0,
        0,
        2,
        118,
        230,
        0,
        0,
        0
      ],
      [
        0,
        0,
        0,
        0,
        0,
        347,
        0,
        3
      ],
      [
        0,
        0,
        0,
        0,
        0,
        0,
        350,
        0
      ],
      [
        2,
        1,
        0,
        0,
        0,
        4,
        0,
        343
      ]
    ]
  },
  "alpha_0.2": {
    "metrics": {
      "mode": "ilp",
      "alpha": 0.2,
      "alpha_mode": "fixed",
      "capacity": 11,
      "headroom": 0.8,
      "ilp_score": 274.7,
      "total_carbon_kg": 515.46,
      "avg_latency_ms": 1.73,
      "p95_latency_ms": 12.0,
      "home_ratio": 0.9014,
      "dropped": 0,
      "n_jobs": 2800,
      "energy_kwh": 1939.5,
      "region_load": {
        "US_West": 350,
        "US_Central": 351,
        "US_East": 354,
        "France": 567,
        "Germany": 131,
        "Korea": 351,
        "India": 350,
        "Japan": 346
      }
    },
    "routing_matrix": [
      [
        347,
        3,
        0,
        0,
        0,
        0,
        0,
        0
      ],
      [
        1,
        344,
        1,
        4,
        0,
        0,
        0,
        0
      ],
      [
        0,
        2,
        348,
        0,
        0,
        0,
        0,
        0
      ],
      [
        0,
        1,
        3,
        330,
        16,
        0,
        0,
        0
      ],
      [
        0,
        0,
        2,
        233,
        115,
        0,
        0,
        0
      ],
      [
        0,
        0,
        0,
        0,
        0,
        347,
        0,
        3
      ],
      [
        0,
        0,
        0,
        0,
        0,
        0,
        350,
        0
      ],
      [
        2,
        1,
        0,
        0,
        0,
        4,
        0,
        343
      ]
    ]
  },
  "alpha_0.25": {
    "metrics": {
      "mode": "ilp",
      "alpha": 0.25,
      "alpha_mode": "fixed",
      "capacity": 11,
      "headroom": 0.8,
      "ilp_score": 338.7,
      "total_carbon_kg": 514.43,
      "avg_latency_ms": 1.86,
      "p95_latency_ms": 12.0,
      "home_ratio": 0.8914,
      "dropped": 0,
      "n_jobs": 2800,
      "energy_kwh": 1939.5,
      "region_load": {
        "US_West": 350,
        "US_Central": 353,
        "US_East": 352,
        "France": 587,
        "Germany": 111,
        "Korea": 351,
        "India": 350,
        "Japan": 346
      }
    },
    "routing_matrix": [
      [
        347,
        3,
        0,
        0,
        0,
        0,
        0,
        0
      ],
      [
        1,
        344,
        1,
        4,
        0,
        0,
        0,
        0
      ],
      [
        0,
        4,
        346,
        0,
        0,
        0,
        0,
        0
      ],
      [
        0,
        1,
        5,
        326,
        18,
        0,
        0,
        0
      ],
      [
        0,
        0,
        0,
        257,
        93,
        0,
        0,
        0
      ],
      [
        0,
        0,
        0,
        0,
        0,
        347,
        0,
        3
      ],
      [
        0,
        0,
        0,
        0,
        0,
        0,
        350,
        0
      ],
      [
        2,
        1,
        0,
        0,
        0,
        4,
        0,
        343
      ]
    ]
  },
  "alpha_0.3": {
    "metrics": {
      "mode": "ilp",
      "alpha": 0.3,
      "alpha_mode": "fixed",
      "capacity": 11,
      "headroom": 0.8,
      "ilp_score": 402.1,
      "total_carbon_kg": 510.24,
      "avg_latency_ms": 1.95,
      "p95_latency_ms": 12.0,
      "home_ratio": 0.8864,
      "dropped": 0,
      "n_jobs": 2800,
      "energy_kwh": 1939.5,
      "region_load": {
        "US_West": 354,
        "US_Central": 348,
        "US_East": 353,
        "France": 596,
        "Germany": 102,
        "Korea": 351,
        "India": 350,
        "Japan": 346
      }
    },
    "routing_matrix": [
      [
        347,
        3,
        0,
        0,
        0,
        0,
        0,
        0
      ],
      [
        5,
        340,
        1,
        4,
        0,
        0,
        0,
        0
      ],
      [
        0,
        3,
        347,
        0,
        0,
        0,
        0,
        0
      ],
      [
        0,
        1,
        5,
        325,
        19,
        0,
        0,
        0
      ],
      [
        0,
        0,
        0,
        267,
        83,
        0,
        0,
        0
      ],
      [
        0,
        0,
        0,
        0,
        0,
        347,
        0,
        3
      ],
      [
        0,
        0,
        0,
        0,
        0,
        0,
        350,
        0
      ],
      [
        2,
        1,
        0,
        0,
        0,
        4,
        0,
        343
      ]
    ]
  },
  "alpha_0.4": {
    "metrics": {
      "mode": "ilp",
      "alpha": 0.4,
      "alpha_mode": "fixed",
      "capacity": 11,
      "headroom": 0.8,
      "ilp_score": 525.8,
      "total_carbon_kg": 442.93,
      "avg_latency_ms": 10.95,
      "p95_latency_ms": 137.0,
      "home_ratio": 0.8182,
      "dropped": 0,
      "n_jobs": 2800,
      "energy_kwh": 1939.5,
      "region_load": {
        "US_West": 405,
        "US_Central": 298,
        "US_East": 356,
        "France": 730,
        "Germany": 134,
        "Korea": 349,
        "India": 182,
        "Japan": 346
      }
    },
    "routing_matrix": [
      [
        344,
        5,
        1,
        0,
        0,
        0,
        0,
        0
      ],
      [
        55,
        289,
        2,
        4,
        0,
        0,
        0,
        0
      ],
      [
        2,
        1,
        347,
        0,
        0,
        0,
        0,
        0
      ],
      [
        0,
        2,
        5,
        324,
        19,
        0,
        0,
        0
      ],
      [
        0,
        0,
        1,
        234,
        115,
        0,
        0,
        0
      ],
      [
        0,
        0,
        0,
        0,
        0,
        347,
        0,
        3
      ],
      [
        0,
        0,
        0,
        168,
        0,
        0,
        182,
        0
      ],
      [
        4,
        1,
        0,
        0,
        0,
        2,
        0,
        343
      ]
    ]
  },
  "alpha_0.5": {
    "metrics": {
      "mode": "ilp",
      "alpha": 0.5,
      "alpha_mode": "fixed",
      "capacity": 11,
      "headroom": 0.8,
      "ilp_score": 620.9,
      "total_carbon_kg": 389.43,
      "avg_latency_ms": 19.83,
      "p95_latency_ms": 137.0,
      "home_ratio": 0.7411,
      "dropped": 0,
      "n_jobs": 2800,
      "energy_kwh": 1939.5,
      "region_load": {
        "US_West": 520,
        "US_Central": 288,
        "US_East": 331,
        "France": 739,
        "Germany": 207,
        "Korea": 358,
        "India": 117,
        "Japan": 240
      }
    },
    "routing_matrix": [
      [
        328,
        14,
        8,
        0,
        0,
        0,
        0,
        0
      ],
      [
        90,
        249,
        6,
        5,
        0,
        0,
        0,
        0
      ],
      [
        2,
        21,
        306,
        21,
        0,
        0,
        0,
        0
      ],
      [
        0,
        2,
        6,
        326,
        16,
        0,
        0,
        0
      ],
      [
        0,
        0,
        5,
        183,
        162,
        0,
        0,
        0
      ],
      [
        3,
        0,
        0,
        0,
        0,
        347,
        0,
        0
      ],
      [
        0,
        0,
        0,
        204,
        29,
        0,
        117,
        0
      ],
      [
        97,
        2,
        0,
        0,
        0,
        11,
        0,
        240
      ]
    ]
  },
  "alpha_0.6": {
    "metrics": {
      "mode": "ilp",
      "alpha": 0.6,
      "alpha_mode": "fixed",
      "capacity": 11,
      "headroom": 0.8,
      "ilp_score": 692.0,
      "total_carbon_kg": 347.41,
      "avg_latency_ms": 33.76,
      "p95_latency_ms": 137.0,
      "home_ratio": 0.6279,
      "dropped": 0,
      "n_jobs": 2800,
      "energy_kwh": 1939.5,
      "region_load": {
        "US_West": 639,
        "US_Central": 321,
        "US_East": 300,
        "France": 775,
        "Germany": 232,
        "Korea": 330,
        "India": 32,
        "Japan": 171
      }
    },
    "routing_matrix": [
      [
        317,
        19,
        7,
        7,
        0,
        0,
        0,
        0
      ],
      [
        91,
        225,
        16,
        18,
        0,
        0,
        0,
        0
      ],
      [
        9,
        54,
        234,
        53,
        0,
        0,
        0,
        0
      ],
      [
        4,
        1,
        9,
        325,
        11,
        0,
        0,
        0
      ],
      [
        1,
        3,
        24,
        152,
        170,
        0,
        0,
        0
      ],
      [
        27,
        2,
        0,
        0,
        0,
        308,
        0,
        13
      ],
      [
        29,
        0,
        10,
        217,
        51,
        0,
        32,
        11
      ],
      [
        161,
        17,
        0,
        3,
        0,
        22,
        0,
        147
      ]
    ]
  },
  "alpha_0.7": {
    "metrics": {
      "mode": "ilp",
      "alpha": 0.7,
      "alpha_mode": "fixed",
      "capacity": 11,
      "headroom": 0.8,
      "ilp_score": 733.2,
      "total_carbon_kg": 312.98,
      "avg_latency_ms": 50.0,
      "p95_latency_ms": 153.0,
      "home_ratio": 0.5318,
      "dropped": 0,
      "n_jobs": 2800,
      "energy_kwh": 1939.5,
      "region_load": {
        "US_West": 752,
        "US_Central": 370,
        "US_East": 405,
        "France": 780,
        "Germany": 241,
        "Korea": 175,
        "India": 0,
        "Japan": 77
      }
    },
    "routing_matrix": [
      [
        321,
        11,
        13,
        2,
        2,
        1,
        0,
        0
      ],
      [
        59,
        223,
        42,
        24,
        2,
        0,
        0,
        0
      ],
      [
        13,
        39,
        238,
        51,
        9,
        0,
        0,
        0
      ],
      [
        5,
        1,
        11,
        324,
        9,
        0,
        0,
        0
      ],
      [
        1,
        10,
        40,
        138,
        161,
        0,
        0,
        0
      ],
      [
        135,
        32,
        0,
        21,
        0,
        154,
        0,
        8
      ],
      [
        18,
        1,
        59,
        207,
        58,
        6,
        0,
        1
      ],
      [
        200,
        53,
        2,
        13,
        0,
        14,
        0,
        68
      ]
    ]
  },
  "alpha_0.75": {
    "metrics": {
      "mode": "ilp",
      "alpha": 0.75,
      "alpha_mode": "fixed",
      "capacity": 11,
      "headroom": 0.8,
      "ilp_score": 744.4,
      "total_carbon_kg": 301.68,
      "avg_latency_ms": 55.67,
      "p95_latency_ms": 204.0,
      "home_ratio": 0.4979,
      "dropped": 0,
      "n_jobs": 2800,
      "energy_kwh": 1939.5,
      "region_load": {
        "US_West": 763,
        "US_Central": 381,
        "US_East": 427,
        "France": 784,
        "Germany": 271,
        "Korea": 104,
        "India": 0,
        "Japan": 70
      }
    },
    "routing_matrix": [
      [
        317,
        14,
        13,
        4,
        1,
        1,
        0,
        0
      ],
      [
        51,
        213,
        56,
        28,
        1,
        1,
        0,
        0
      ],
      [
        13,
        31,
        234,
        55,
        17,
        0,
        0,
        0
      ],
      [
        4,
        5,
        8,
        323,
        10,
        0,
        0,
        0
      ],
      [
        2,
        6,
        44,
        128,
        170,
        0,
        0,
        0
      ],
      [
        160,
        44,
        1,
        41,
        9,
        82,
        0,
        13
      ],
      [
        16,
        0,
        66,
        196,
        63,
        7,
        0,
        2
      ],
      [
        200,
        68,
        5,
        9,
        0,
        13,
        0,
        55
      ]
    ]
  },
  "alpha_0.8": {
    "metrics": {
      "mode": "ilp",
      "alpha": 0.8,
      "alpha_mode": "fixed",
      "capacity": 11,
      "headroom": 0.8,
      "ilp_score": 749.9,
      "total_carbon_kg": 296.56,
      "avg_latency_ms": 61.04,
      "p95_latency_ms": 204.0,
      "home_ratio": 0.4693,
      "dropped": 0,
      "n_jobs": 2800,
      "energy_kwh": 1939.5,
      "region_load": {
        "US_West": 753,
        "US_Central": 386,
        "US_East": 415,
        "France": 803,
        "Germany": 316,
        "Korea": 65,
        "India": 0,
        "Japan": 62
      }
    },
    "routing_matrix": [
      [
        315,
        12,
        9,
        8,
        2,
        4,
        0,
        0
      ],
      [
        51,
        194,
        70,
        34,
        0,
        1,
        0,
        0
      ],
      [
        13,
        33,
        212,
        59,
        33,
        0,
        0,
        0
      ],
      [
        3,
        7,
        9,
        323,
        8,
        0,
        0,
        0
      ],
      [
        2,
        7,
        40,
        121,
        180,
        0,
        0,
        0
      ],
      [
        155,
        57,
        10,
        57,
        19,
        41,
        0,
        11
      ],
      [
        21,
        2,
        59,
        184,
        74,
        8,
        0,
        2
      ],
      [
        193,
        74,
        6,
        17,
        0,
        11,
        0,
        49
      ]
    ]
  },
  "alpha_0.9": {
    "metrics": {
      "mode": "ilp",
      "alpha": 0.9,
      "alpha_mode": "fixed",
      "capacity": 11,
      "headroom": 0.8,
      "ilp_score": 758.9,
      "total_carbon_kg": 291.05,
      "avg_latency_ms": 66.03,
      "p95_latency_ms": 225.0,
      "home_ratio": 0.4443,
      "dropped": 0,
      "n_jobs": 2800,
      "energy_kwh": 1939.5,
      "region_load": {
        "US_West": 736,
        "US_Central": 399,
        "US_East": 425,
        "France": 785,
        "Germany": 380,
        "Korea": 36,
        "India": 0,
        "Japan": 39
      }
    },
    "routing_matrix": [
      [
        306,
        11,
        15,
        13,
        4,
        1,
        0,
        0
      ],
      [
        46,
        189,
        73,
        41,
        0,
        1,
        0,
        0
      ],
      [
        9,
        38,
        193,
        59,
        51,
        0,
        0,
        0
      ],
      [
        2,
        13,
        9,
        316,
        10,
        0,
        0,
        0
      ],
      [
        3,
        9,
        40,
        112,
        186,
        0,
        0,
        0
      ],
      [
        142,
        60,
        24,
        65,
        29,
        23,
        0,
        7
      ],
      [
        19,
        3,
        70,
        154,
        98,
        5,
        0,
        1
      ],
      [
        209,
        76,
        1,
        25,
        2,
        6,
        0,
        31
      ]
    ]
  },
  "alpha_1": {
    "metrics": {
      "mode": "ilp",
      "alpha": 1.0,
      "alpha_mode": "fixed",
      "capacity": 11,
      "headroom": 0.8,
      "ilp_score": 730.8,
      "total_carbon_kg": 302.1,
      "avg_latency_ms": 113.46,
      "p95_latency_ms": 238.0,
      "home_ratio": 0.1271,
      "dropped": 0,
      "n_jobs": 2800,
      "energy_kwh": 1939.5,
      "region_load": {
        "US_West": 718,
        "US_Central": 384,
        "US_East": 415,
        "France": 838,
        "Germany": 391,
        "Korea": 24,
        "India": 0,
        "Japan": 30
      }
    },
    "routing_matrix": [
      [
        93,
        51,
        45,
        106,
        48,
        5,
        0,
        2
      ],
      [
        87,
        60,
        48,
        102,
        45,
        5,
        0,
        3
      ],
      [
        94,
        51,
        48,
        100,
        50,
        4,
        0,
        3
      ],
      [
        96,
        37,
        53,
        100,
        59,
        2,
        0,
        3
      ],
      [
        89,
        40,
        56,
        106,
        51,
        1,
        0,
        7
      ],
      [
        93,
        42,
        56,
        101,
        52,
        2,
        0,
        4
      ],
      [
        69,
        54,
        53,
        119,
        48,
        1,
        0,
        6
      ],
      [
        97,
        49,
        56,
        104,
        38,
        4,
        0,
        2
      ]
    ]
  },
  "alpha_auto": {
    "metrics": {
      "mode": "ilp",
      "alpha": 0.544,
      "alpha_mode": "auto",
      "capacity": 11,
      "headroom": 0.8,
      "ilp_score": 636.9,
      "total_carbon_kg": 312.62,
      "avg_latency_ms": 33.85,
      "p95_latency_ms": 142.0,
      "home_ratio": 0.65,
      "dropped": 0,
      "n_jobs": 2800,
      "energy_kwh": 1939.5,
      "region_load": {
        "US_West": 588,
        "US_Central": 334,
        "US_East": 364,
        "France": 701,
        "Germany": 273,
        "Korea": 271,
        "India": 92,
        "Japan": 177
      }
    },
    "routing_matrix": [
      [
        312,
        19,
        11,
        5,
        1,
        2,
        0,
        0
      ],
      [
        70,
        231,
        29,
        19,
        1,
        0,
        0,
        0
      ],
      [
        2,
        23,
        274,
        35,
        16,
        0,
        0,
        0
      ],
      [
        5,
        1,
        10,
        316,
        18,
        0,
        0,
        0
      ],
      [
        1,
        3,
        20,
        147,
        179,
        0,
        0,
        0
      ],
      [
        51,
        20,
        3,
        13,
        2,
        253,
        0,
        8
      ],
      [
        22,
        0,
        15,
        156,
        56,
        3,
        92,
        6
      ],
      [
        125,
        37,
        2,
        10,
        0,
        13,
        0,
        163
      ]
    ]
  }
}